nuxbt/__init__.py
nuxbt/agent.py
nuxbt/bluez.py
nuxbt/cli.py
nuxbt/controller/__init__.py
nuxbt/controller/controller.py
nuxbt/controller/input.py
nuxbt/controller/protocol.py
nuxbt/controller/sdp/switch-controller.xml
nuxbt/controller/server.py
nuxbt/controller/utils.py
nuxbt/gui.py
nuxbt/logging.py
nuxbt/nuxbt.py
nuxbt/tui.py
nuxbt/web/__init__.py
nuxbt/web/app.py
nuxbt/web/cert.py
nuxbt/web/client/.gitignore
nuxbt/web/client/README.md
nuxbt/web/client/eslint.config.js
nuxbt/web/client/index.html
nuxbt/web/client/package-lock.json
nuxbt/web/client/package.json
nuxbt/web/client/postcss.config.js
nuxbt/web/client/public/vite.svg
nuxbt/web/client/src/App.css
nuxbt/web/client/src/App.tsx
nuxbt/web/client/src/assets/pro-controller.svg
nuxbt/web/client/src/assets/react.svg
nuxbt/web/client/src/components/ControllerInput.tsx
nuxbt/web/client/src/components/ControllerVisual.tsx
nuxbt/web/client/src/components/KeyBindings.tsx
nuxbt/web/client/src/components/MacroControls.test.tsx
nuxbt/web/client/src/components/MacroControls.tsx
nuxbt/web/client/src/components/ThemeToggle.tsx
nuxbt/web/client/src/defaults.ts
nuxbt/web/client/src/index.css
nuxbt/web/client/src/main.tsx
nuxbt/web/client/src/socket.ts
nuxbt/web/client/src/test/setup.ts
nuxbt/web/client/src/types.ts
nuxbt/web/client/tailwind.config.js
nuxbt/web/client/tsconfig.app.json
nuxbt/web/client/tsconfig.json
nuxbt/web/client/tsconfig.node.json
nuxbt/web/client/vite.config.ts
nuxbt/web/static/css/main.css
nuxbt/web/static/dist/.vite/manifest.json
nuxbt/web/static/dist/assets/index-B2M8y6Fe.css
nuxbt/web/static/dist/assets/index-D_UVsmZi.js
nuxbt/web/static/dist/assets/pro-controller-D6NA8UIM.svg
nuxbt/web/static/dist/vite.svg
nuxbt/web/static/favicon.png
nuxbt/web/static/joyconl.svg
nuxbt/web/static/joyconr.svg
nuxbt/web/static/js/main.js
nuxbt/web/static/js/socket.io.js
nuxbt/web/static/js/socket.io.js.map
nuxbt/web/static/procon-transparent.svg
nuxbt/web/static/procon.svg
nuxbt/web/templates/index.html
nuxbt-3.1.1.dist-info/METADATA
nuxbt-3.1.1.dist-info/WHEEL
nuxbt-3.1.1.dist-info/entry_points.txt
nuxbt-3.1.1.dist-info/licenses/LICENSE
nuxbt-3.1.1.dist-info/RECORD
