Metadata-Version: 2.4
Name: nuxbt
Version: 3.1.1
Summary: Control your Nintendo Switch through a website, terminal, or macro.
License: MIT
License-File: LICENSE
Author: Hannah Brown
Author-email: hannah@hannahis.gay
Requires-Python: >=3.11,<4.0
Classifier: Development Status :: 3 - Alpha
Classifier: Intended Audience :: Developers
Classifier: License :: OSI Approved :: MIT License
Classifier: Operating System :: OS Independent
Classifier: Programming Language :: Python :: 3
Classifier: Programming Language :: Python :: 3.11
Classifier: Programming Language :: Python :: 3.12
Classifier: Programming Language :: Python :: 3.13
Classifier: Programming Language :: Python :: 3.14
Classifier: Topic :: Software Development :: Libraries :: Python Modules
Requires-Dist: Flask (>=2.1.3)
Requires-Dist: Flask-SocketIO (>=5.3.4)
Requires-Dist: PyGObject (>=3.42.0,<4.0.0)
Requires-Dist: Werkzeug (>=2.0.3)
Requires-Dist: a2wsgi (>=1.10.10,<2.0.0)
Requires-Dist: blessed (>=1.17.10)
Requires-Dist: click (>=8.3.1,<9.0.0)
Requires-Dist: cryptography (>=3.3.2)
Requires-Dist: dbus-python (>=1.2.16)
Requires-Dist: itsdangerous (>=2.0.1)
Requires-Dist: jinja2 (>=3.0.3)
Requires-Dist: psutil (>=5.6.6)
Requires-Dist: pynput (>=1.7.1)
Requires-Dist: pyqt6 (>=6.10.1,<7.0.0)
Requires-Dist: uvicorn (>=0.38.0,<0.39.0)
Project-URL: Code, https://github.com/hannahbee91/nuxbt
Project-URL: Issue tracker, https://github.com/hannahbee91/nuxbt/issues
